{
  "name": "Belgium",
  "last_updated": "2026-04-30",
  "source_monthly": "FEBIAC (Fédération Belge de l'Industrie de l'Automobile et du Cycle)",
  "source_annual": "FEBIAC (Fédération Belge de l'Industrie de l'Automobile et du Cycle)",
  "annual": {
    "labels": [
      "2015",
      "2016",
      "2017",
      "2018",
      "2019",
      "2020",
      "2021",
      "2022",
      "2023",
      "2024",
      "2025"
    ],
    "bev": [
      1300,
      1641,
      1934,
      2939,
      10657,
      14706,
      25613,
      38791,
      93285,
      127703,
      143849
    ],
    "phev": [
      2800,
      5400,
      8500,
      5300,
      12947,
      26900,
      60360,
      60116,
      86700,
      66793,
      42330
    ],
    "hybrid": [
      13000,
      18000,
      22000,
      27000,
      33000,
      45000,
      68000,
      52000,
      59000,
      41242,
      47699
    ],
    "petrol": [
      200000,
      250000,
      295000,
      348000,
      310000,
      225000,
      215000,
      175000,
      154000,
      187380,
      168449
    ],
    "diesel": [
      285000,
      270000,
      220000,
      165000,
      169000,
      109000,
      97000,
      67000,
      60000,
      21965,
      12443
    ],
    "other": [
      -1034,
      -4911,
      -876,
      1393,
      15355,
      9688,
      26837,
      19102,
      23690,
      3194,
      0
    ]
  },
  "monthly": {
    "labels": [
      "2024-01",
      "2024-02",
      "2024-03",
      "2024-04",
      "2024-05",
      "2024-06",
      "2024-07",
      "2024-08",
      "2024-09",
      "2024-10",
      "2024-11",
      "2024-12",
      "2025-01",
      "2025-02",
      "2025-03",
      "2025-04",
      "2025-05",
      "2025-06",
      "2025-07",
      "2025-08",
      "2025-09",
      "2025-10",
      "2025-11",
      "2025-12",
      "2026-01",
      "2026-02",
      "2026-03"
    ],
    "total": [
      31900,
      28000,
      39800,
      30500,
      32600,
      32500,
      28000,
      22500,
      36000,
      32500,
      28800,
      32691,
      28800,
      24000,
      36000,
      27500,
      28500,
      30500,
      27000,
      22000,
      31500,
      28000,
      28500,
      30700,
      27500,
      24500,
      33000
    ]
  },
  "data_quality": "national_registration_authority_primary_source"
}
