{
  "monthly": {
    "labels": [
      "2015",
      "2016",
      "2017",
      "2018",
      "2019",
      "2020",
      "2021",
      "2022",
      "2023",
      "2024",
      "2025"
    ],
    "total": [
      125000,
      148000,
      154000,
      154000,
      155000,
      112000,
      120000,
      107000,
      115000,
      107000,
      110000
    ]
  },
  "annual": {
    "labels": [
      "2019",
      "2020",
      "2021",
      "2022",
      "2023",
      "2024",
      "2025"
    ],
    "bev": [
      700,
      800,
      4000,
      5400,
      9200,
      12840,
      15400
    ],
    "phev": [
      900,
      900,
      2500,
      3200,
      4000,
      4280,
      4950
    ],
    "hybrid": [
      8000,
      7000,
      10000,
      11000,
      15000,
      16070,
      18700
    ],
    "petrol": [
      117000,
      79000,
      82000,
      70000,
      73000,
      63000,
      62000
    ],
    "diesel": [
      28400,
      24300,
      21500,
      17400,
      13800,
      10810,
      9950
    ],
    "other": [
      0,
      0,
      0,
      0,
      0,
      0,
      0
    ]
  },
  "last_updated": "2026-04-24T18:00:00.000000Z",
  "source_monthly": "MIA (Motor Industry Association New Zealand) / IEA Global EV Outlook 2025",
  "source_annual": "MIA (Motor Industry Association New Zealand)"
}
